{
    "group": "AI",
    "content": "Mistral AI beeindruckt mit hocheffizientem Mistral 7B",
    "short_title": "Mistral 7B",
    "start": "2023-09-27",
    "details": "### Mistral 7B: Das kleine Modell, das die Großen schlug\n\nEnde September 2023 sorgte das neu gegründete Pariser Startup Mistral AI für eine Sensation, indem es sein erstes Modell, Mistral 7B, einfach über einen Torrent-Link veröffentlichte. Trotz seiner geringen Größe von nur 7 Milliarden Parametern übertraf dieses Modell in vielen Benchmarks deutlich größere Modelle wie Llama 2 13B und war in seiner Leistungsklasse unübertroffen.\n\n#### Die Rolle der KI im Durchbruch\n\nDer Durchbruch von Mistral 7B lag in seiner hocheffizienten KI-Architektur. Das Modell nutzte fortschrittliche Techniken wie **Grouped-Query Attention (GQA)** für eine schnellere Inferenz und **Sliding Window Attention (SWA)**, um längere Sequenzen bei geringerem Speicherbedarf zu verarbeiten. Diese Innovationen ermöglichten es dem Modell, eine Leistung zu erzielen, für die normalerweise viel größere Modelle erforderlich waren.\n\n#### Bedeutung und potenzieller Einfluss\n\nMistral 7B hat bewiesen, dass Größe nicht alles ist. Es zeigte, dass durch intelligente Architekturentscheidungen auch kleine, effiziente Modelle extrem leistungsfähig sein können. Dies machte es zum Liebling der Open-Source-Community, da es auf handelsüblicher Hardware ausgeführt werden konnte. Mistral etablierte sich über Nacht als führendes europäisches KI-Unternehmen und als Pionier für effiziente KI-Modelle."
}