{
    "group": "Science",
    "content": "Parker Solar Probe \"berührt\" erstmals die Sonne",
    "short_title": "Parker Solar Probe",
    "start": "2021-12-14",
    "details": "### Eine Raumsonde fliegt durch die Atmosphäre der Sonne\n\nDie NASA gab bekannt, dass ihre Parker Solar Probe am 28. April 2021 als erstes von Menschen geschaffenes Objekt offiziell in die obere Atmosphäre der Sonne, die Korona, eingetreten war. Die Sonde überlebte die extremen Temperaturen und die Strahlung, um beispiellose direkte Messungen der Partikel und Magnetfelder der Sonne zu sammeln.\n\n#### Die Rolle der KI im Durchbruch\n\nDie Sonde muss vollständig autonom operieren, da die Kommunikationszeit zur Erde zu lang ist, um in Echtzeit zu steuern. Eine fortschrittliche KI an Bord namens \"Fault Management System\" ist für das Überleben der Sonde unerlässlich. Sie überwacht Tausende von Sensoren und kann bei Problemen – wie einer Überhitzung – selbstständig Korrekturmaßnahmen einleiten, z. B. die Sonde neu ausrichten, um den empfindlichen Hitzeschild zu positionieren.\n\n#### Bedeutung und potenzieller Einfluss\n\nDie Parker Solar Probe löst einige der größten Rätsel der Sonnenphysik, wie z. B. warum die Korona millionenfach heißer ist als die sichtbare Oberfläche der Sonne und was den Sonnenwind auf Überschallgeschwindigkeit beschleunigt. Das Verständnis dieser Prozesse ist entscheidend, um das Weltraumwetter vorherzusagen, das Satelliten, Stromnetze und Astronauten auf der Erde und im All gefährden kann."
}